authorize_networks_cli/__init__.py
authorize_networks_cli/authorize_kubernetes.py
authorize_networks_cli/authorize_sql.py
authorize_networks_cli/main.py
authorize_networks_cli/save_config.py
authorize_networks_cli/util.py
gcloud_network_authorizer-0.0.6.dist-info/LICENSE
gcloud_network_authorizer-0.0.6.dist-info/METADATA
gcloud_network_authorizer-0.0.6.dist-info/WHEEL
gcloud_network_authorizer-0.0.6.dist-info/entry_points.txt
gcloud_network_authorizer-0.0.6.dist-info/top_level.txt
gcloud_network_authorizer-0.0.6.dist-info/RECORD
