Metadata-Version: 2.1
Name: gcloud-network-authorizer
Version: 0.0.6
License-File: LICENSE
Requires-Dist: click
Requires-Dist: requests
